README.md
setup.cfg
setup.py
src/jailbase/__init__.py
src/jailbase/cli.py
src/jailbase/jailbase.py
src/jailbase.egg-info/PKG-INFO
src/jailbase.egg-info/SOURCES.txt
src/jailbase.egg-info/dependency_links.txt
src/jailbase.egg-info/entry_points.txt
src/jailbase.egg-info/requires.txt
src/jailbase.egg-info/top_level.txt